Workbook

Sheet Лист1
B2: Приложение к Разделу 6 Документации
A3: Обоснование начальной (максимальной) цены договора
B4: Дата подготовки: 31 августа 2026 года
A6: Способ проведения закупки, предмет закупки | C6: Сбор коммерческих предложений. Разработка и реализация комплексной юбилейной программы, посвященной 25-летию АО «ГТЛК».
A7: Кол-во, ед. измерения | C7: Объем фактически выполненых услуг определяется в ходе исполнения Договора в пределах максимального значения цены договора, исходя из единичных расценок каждого вида работы, 1 усл. ед.
A8: Краткая характеристики объекта закупки | C8: Разработка и реализация комплексной юбилейной программы, посвященной 25-летию АО «ГТЛК».
A9: Используемый метод определения НМЦед с обоснованием выбора данного метода | C9: Максимальное значение цены договора составляет 160 000 000 , вкл. НДС (пп. 8.11.4.3 п. 8.11. Положения о закупке товаров, работ и услуг для нужд АО «ГТЛК»). Цена единицы Услуги определена в соответствии с требованиями п.8.4.5 .Положения о закупке товаров, работ и услуг для нужд АО «ГТЛК методом сопоставимых рыночных цен (анализ рынка), суммарная стоимость начальных (максимальных) единичных расценок составляет: 69 472 955 рублей 16 копеек.
A10: РАСЧЕТ НМЦед
A11: № | B11: Наименование товара, услуги (работы) | C11: Единица измерения | D11: Исполнитель №1 | E11: Исполнитель №2 | F11: Исполнитель №3 | G11: Исполнитель №4 | H11: {Поставщик_4} | I11: {Поставщик_5} | J11: {Поставщик_6} | K11: {Поставщик_7} | L11: {Поставщик_8} | M11: {Поставщик_9} | N11: {Поставщик_10} | O11: {Поставщик_11} | P11: {Поставщик_12} | Q11: {Поставщик_13} | R11: {Поставщик_14} | S11: {Поставщик_15} | T11: {Поставщик_16} | U11: {Поставщик_17} | V11: {Поставщик_18} | W11: {Поставщик_19} | X11: {Поставщик_20} | Y11: Средняя цена (руб.) | Z11: Минимальная НМЦед из предложенных (руб., вкл. НДС)
D12: цена | E12: цена | F12: цена | G12: цена | H12: Цена (руб.) | I12: Цена (руб.) | J12: Цена (руб.) | K12: Цена (руб.) | L12: Цена (руб.) | M12: Цена (руб.) | N12: Цена (руб.) | O12: Цена (руб.) | P12: Цена (руб.) | Q12: Цена (руб.) | R12: Цена (руб.) | S12: Цена (руб.) | T12: Цена (руб.) | U12: Цена (руб.) | V12: Цена (руб.) | W12: Цена (руб.) | X12: Цена (руб.)
A13: 1 | B13: (1–2 чел.) — игра на площадке 4×4×4 м, обучение 2 минуты, игра 1 минута, 2 профессиональных аниматора и инвентарь. | C13: 1 усл | D13: =[1]Лист4!D4 -> 126000 | E13: =[2]Лист4!D5 -> 152500 | F13: =[3]Лист4!D5 -> 178120 | G13: =[4]Лист4!D4 -> 157080 | Z13: =MIN(D13:G13) -> 126000
A14: 2 | B14: (от 20 до 100 чел.) — командообразующее мероприятие в формате квеста, командного соревнования или интеллектуальной игры с профессиональным ведущим, сценарной разработкой под заказчика, всем реквизитом. | C14: 1 час | D14: =[1]Лист4!D5 -> 157500 | E14: =[2]Лист4!D6 -> 231800 | F14: =[3]Лист4!D6 -> 183000 | G14: =[4]Лист4!D5 -> 193746 | Z14: =MIN(D14:G14) -> 157500
A15: 3 | B15: (от 200 до 2000 чел.) — масштабный тематический квест для детей с авторским сценарием, тематическими костюмами для ведущих и персонажей, реквизитом, с опытом проведения крупных детских мероприятий для государственных и корпоративных клиентов. | C15: 1 час | D15: =[1]Лист4!D6 -> 2100 | E15: =[2]Лист4!D7 -> 2196 | F15: =[3]Лист4!D7 -> 1220 | G15: =[4]Лист4!D6 -> 2194.5 | Z15: =MIN(D15:G15) -> 1220
A16: 4 | B16: Командная деловая игра или бизнес-симуляция с профессиональным ведущим-фасилитатором, методологической разработкой под тематику заказчика. | C16: 1 час | D16: =[1]Лист4!D7 -> 210000 | E16: =[2]Лист4!D8 -> 250100 | F16: =[3]Лист4!D8 -> 292800 | G16: =[4]Лист4!D7 -> 267750 | Z16: =MIN(D16:G16) -> 210000
A17: 5 | B17: Организация и проведение интерактива с пиньятой — профессиональный аниматор с опытом проведения интерактивных активностей на корпоративных мероприятиях, изготовление тематической пиньяты под концепцию мероприятия. | C17: 1 выступление | D17: =[1]Лист4!D8 -> 52500 | E17: =[2]Лист4!D9 -> 70760 | F17: =[3]Лист4!D9 -> 61000 | G17: =[4]Лист4!D8 -> 63000 | Z17: =MIN(D17:G17) -> 52500
A18: 6 | B18: Тематический квест на городских локациях с авторским сценарием, разработкой маршрута, реквизитом, профессиональными ведущими и техническим сопровождением. | C18: 1 чел | D18: =[1]Лист4!D9 -> 1575 | E18: =[2]Лист4!D10 -> 2074 | F18: =[3]Лист4!D10 -> 1220 | G18: =[4]Лист4!D9 -> 1550 | Z18: =MIN(D18:G18) -> 1220
A19: 7 | B19: Услуга аниматора — актёр, выпускник театрального училища, с опытом работы в профессиональном театре и авторскими интерактивными программами для смешанной и детской аудитории, 10 лет+. | C19: 1 чел./час | D19: =[1]Лист4!D10 -> 15120 | E19: =[2]Лист4!D11 -> 18300 | F19: =[3]Лист4!D11 -> 12200 | G19: =[4]Лист4!D10 -> 19950 | Z19: =MIN(D19:G19) -> 12200
A20: 8 | B20: Услуга аниматора — профессиональный артист с авторскими интерактивными шоу-программами в формате ростовых костюмов и световых шоу с криоэффектом, опытом работы на корпоративных мероприятиях 10+ лет. | C20: 1 чел./час | D20: =[1]Лист4!D11 -> 42000 | E20: =[2]Лист4!D12 -> 48800 | F20: =[3]Лист4!D12 -> 42700 | G20: =[4]Лист4!D11 -> 47250 | Z20: =MIN(D20:G20) -> 42000
A21: 9 | B21: Услуга аниматора — профессиональный специалист по интерактивному взаимодействию с аудиторией с профильным актёрским или режиссёрским образованием, авторскими программами для корпоративных форматов, опытом работы с группами от 30 до 200 человек, 10 лет+. | C21: 1 чел./час | D21: =[1]Лист4!D12 -> 15750 | E21: =[2]Лист4!D13 -> 21106 | F21: =[3]Лист4!D13 -> 12200 | G21: =[4]Лист4!D12 -> 15645 | Z21: =MIN(D21:G21) -> 12200
A22: 10 | B22: Выступление государственного фольклорного ансамбля, сочетающее народное пение, хореографию и музыкальное искусство на профессиональной основе. | C22: 1 выступление | D22: =[1]Лист4!D13 -> 504000 | E22: =[2]Лист4!D14 -> 610000 | F22: =[3]Лист4!D14 -> 549000 | G22: =[4]Лист4!D13 -> 735000 | Z22: =MIN(D22:G22) -> 504000
A23: 11 | B23: Выступление армейского ансамбля песни и пляски. | C23: 1 выступление | D23: =[1]Лист4!D14 -> 646800 | E23: =[2]Лист4!D15 -> 786900 | F23: =[3]Лист4!D15 -> 732000 | G23: =[4]Лист4!D14 -> 735000 | Z23: =MIN(D23:G23) -> 646800
A24: 12 | B24: Аренда 1 этажа концертного зала на 1200 человек в радиусе 2 километров от Гостиного двора | C24: 1 усл/4 часа | D24: =[1]Лист4!D15 -> 149100 | E24: =[2]Лист4!D16 -> 176900 | F24: =[3]Лист4!D16 -> 170800 | G24: =[4]Лист4!D15 -> 155400 | Z24: =MIN(D24:G24) -> 149100
... A441: 429 | B441: Театрализованное световое шоу в флюоресцентных костюмах с авторской хореографией и несколькими сменами светового реквизита. | C441: 1 выступление | D441: =[1]Лист4!D432 -> 187110 | E441: =[2]Лист4!D433 -> 250100 | F441: =[3]Лист4!D433 -> 244000 | G441: =[4]Лист4!D432 -> 199500 | Z441: =MIN(D441:G441) -> 187110
A442: Всего: | D442: =SUM(D13:D441) -> 70003282 | E442: =SUM(E13:E441) -> 91692352 | F442: =SUM(F13:F441) -> 93079274 | G442: =SUM(G13:G441) -> 84861505 | Z442: 69472955
Y443: Итого:
A444: На основании проведенного анализа рынка и расчетов, НМЦед составляет: руб.:69 472 955 рублей 16 копеек.
